<annotation>
	<folder>Trichoderma</folder>
	<filename>2_trichoderma_x.jpg</filename>
	<path>C:\Users\nadyu\PycharmProjects\mold_detector\tfod\Tensorflow\workspace\images\collectedimages\Trichoderma\2_trichoderma_x.jpg</path>
	<source>
		<database>Unknown</database>
	</source>
	<size>
		<width>275</width>
		<height>183</height>
		<depth>3</depth>
	</size>
	<segmented>0</segmented>
	<object>
		<name>Trichoderma</name>
		<pose>Unspecified</pose>
		<truncated>0</truncated>
		<difficult>0</difficult>
		<bndbox>
			<xmin>29</xmin>
			<ymin>48</ymin>
			<xmax>123</xmax>
			<ymax>123</ymax>
		</bndbox>
	</object>
	<object>
		<name>Trichoderma</name>
		<pose>Unspecified</pose>
		<truncated>0</truncated>
		<difficult>0</difficult>
		<bndbox>
			<xmin>162</xmin>
			<ymin>61</ymin>
			<xmax>239</xmax>
			<ymax>108</ymax>
		</bndbox>
	</object>
</annotation>
